[
  {
    "名前": "Mystic",
    "種類": "magic",
    "ダメージ": 10,
    "スピード": null,
    "クリティカル率": null,
    "マナコスト": -15,
    "ノックバック": null
  },
  {
    "名前": "Adept",
    "種類": "magic",
    "ダメージ": null,
    "スピード": null,
    "クリティカル率": null,
    "マナコスト": -15,
    "ノックバック": 5
  },
  {
    "名前": "Masterful",
    "種類": "magic",
    "ダメージ": 15,
    "スピード": null,
    "クリティカル率": null,
    "マナコスト": -15,
    "ノックバック": 5
  },
  {
    "名前": "Inept",
    "種類": "magic",
    "ダメージ": null,
    "スピード": null,
    "クリティカル率": null,
    "マナコスト": 10,
    "ノックバック": null
  },
  {
    "名前": "Ignorant",
    "種類": "magic",
    "ダメージ": 10,
    "スピード": null,
    "クリティカル率": null,
    "マナコスト": 20,
    "ノックバック": null
  },
  {
    "名前": "Deranged",
    "種類": "magic",
    "ダメージ": -10,
    "スピード": null,
    "クリティカル率": null,
    "マナコスト": null,
    "ノックバック": -10
  },
  {
    "名前": "Intense",
    "種類": "magic",
    "ダメージ": 10,
    "スピード": null,
    "クリティカル率": null,
    "マナコスト": 15,
    "ノックバック": null
  },
  {
    "名前": "Taboo",
    "種類": "magic",
    "ダメージ": null,
    "スピード": 10,
    "クリティカル率": null,
    "マナコスト": 10,
    "ノックバック": 10
  },
  {
    "名前": "Celestial",
    "種類": "magic",
    "ダメージ": 10,
    "スピード": -10,
    "クリティカル率": null,
    "マナコスト": -10,
    "ノックバック": 10
  },
  {
    "名前": "Furious",
    "種類": "magic",
    "ダメージ": 15,
    "スピード": null,
    "クリティカル率": null,
    "マナコスト": 20,
    "ノックバック": 15
  },
  {
    "名前": "Manic",
    "種類": "magic",
    "ダメージ": -10,
    "スピード": 10,
    "クリティカル率": null,
    "マナコスト": 10,
    "ノックバック": null
  },
  {
    "名前": "Mythical",
    "種類": "magic",
    "ダメージ": 15,
    "スピード": 10,
    "クリティカル率": 5,
    "マナコスト": -10,
    "ノックバック": 15
  }
]
